ExpreLev/ExpreLevEpi.py
ExpreLev/ExpreLevExon.py
ExpreLev/ExpreLevGene.py
ExpreLev/__init__.py
ExpreLev/__main__.py
ExpreLev/_version.py
ExpreLev-1.0.6.dist-info/LICENSE
ExpreLev-1.0.6.dist-info/METADATA
ExpreLev-1.0.6.dist-info/WHEEL
ExpreLev-1.0.6.dist-info/entry_points.txt
ExpreLev-1.0.6.dist-info/top_level.txt
ExpreLev-1.0.6.dist-info/RECORD
