Metadata-Version: 2.1
Name: ExpreLev
Version: 1.0.6
Summary: TPM/CPM/FPKM analysis
Home-page: https://pypi.org/project/ExpreLev/
Author: Benxia Hu
Author-email: hubenxia@gmail.com
License: UNKNOWN
Platform: UNKNOWN
Classifier: Programming Language :: Python :: 3
Classifier: License :: OSI Approved :: MIT License
Classifier: Operating System :: OS Independent
Requires-Python: >=3.6
Requires-Dist: numpy (==1.23.1)
Requires-Dist: pandas (==1.4.3)
Requires-Dist: pyranges (==0.0.117)
